{
  "common": {
    "back": "Lesu",
    "language": "Vosa",
    "timezone": "Gauna",
    "logout": "Curu i tuba 🚪",
    "loading": "Wawa..."
  },
  "dashboard": {
    "title": "Katakata ni Gonevuli ni Elmore High",
    "idCardTitle": "★ Kadi ni Gonevuli Vakadonui ★",
    "statusActive": "Bula",
    "classGrade": "Giredi ni Kalasi:",
    "homeroom": "Rumunikalasi:",
    "email": "Imeli:",
    "clubsJoined": "Kalavo Leweni:",
    "campusServices": "Veiqaravi ni Koronivuli",
    "advocacyTitle": "Veitokoni Vuli",
    "advocacyDesc": "Veivuke ni vuli & iLawalawa",
    "hallwayReminders": "📌 Vakananumi ni Gaunisala"
  },
  "advocacy": {
    "header": "Veitokoni Vuli",
    "studyGroupsBtn": "iLawalawa ni Vuli 📚",
    "welcomeTitle": "Bula vinaka ki na Veitokoni Vuli!",
    "welcomeDesc": "E tiko beka na leqa vakaivola? Vinakata na veidusimaki ena gauna mai muri? Se vinakata ga me tauyavutaka e dua na iLawalawa ni Vuli? Sa tiko na Mataveisoqosoqo ni Gonevuli e Elmore me veivuke! Vakatututaka e dua na kerekere ka na veivuke ko Anais Watterson, na noda iLiuliu ni Veika Vuli!",
    "submitRequest": "Vakatututaka e Dua na Kerekere",
    "typeLabel": "Mataqali Kerekere",
    "typeProblem": "Leqa Vakaivola",
    "typeGuidance": "Veidusimaki Vakaivola",
    "typeGroup": "Kerekere ni Lawalawa Vuli",
    "titleLabel": "Yaca",
    "titlePlaceholder": "kena ivakaraitaki: Vinakata na veivuke ena kalasi nei Mr. Small",
    "descLabel": "iVakamacala",
    "descPlaceholder": "Vakamacalataka vakamatata na kemu ituvaki...",
    "btnSubmit": "Vakatututaka na Kerekere ✨",
    "btnSubmitting": "Vakatututaka tiko...",
    "allRequests": "Kerekere Kece ni Gonevuli",
    "yourRequests": "Nomu Kerekere sa Oti",
    "noRequests": "Sega ni kune e dua na kerekere.",
    "statusPending": "Wawa tiko",
    "statusResolved": "Sa Walia",
    "statusRejected": "Katalau",
    "statusRevoked": "Bokoci",
    "requestedBy": "Kerea ko",
    "anaisResponse": "🐰 iSau nei Anais",
    "vetoTitle": "⚖️ Vakatulewa ni Gonevuli (Leca na Yavu ni Vakavuvuli)",
    "revokedBy": "Bokoci mai vei:",
    "adminActionReject": "Sega ni ciqoma ❌",
    "adminActionResolve": "Walia ✅",
    "vetoLabel": "Vakatulewa cecere: Bokoci baleta na leca ni Yavu ni Vakavuvuli",
    "vetoPlaceholder": "Tukuna na lawa ni Yavu ni Vakavuvuli ni Mataveisoqosoqo ni Gonevuli e Elmore e leca...",
    "btnRevoke": "Bokoca na Vakatulewa ⚖️"
  },
  "study_groups": {
    "header": "iLawalawa ni Vuli & Vuli Vakatabakidua",
    "findGroup": "Vaqara e dua na iLawalawa ni Vuli",
    "searchPlaceholder": "Vaqara ena lesoni se rumunikalasi...",
    "btnSearch": "Vaqara 🔍",
    "noGroups": "Sega ni kune na ilawalawa ni vuli. Cava o sega ni tekivuna kina e dua?",
    "createdBy": "Bulia ko:",
    "startGroup": "Tekivutaka e dua na iLawalawa ni Vuli Vou",
    "namePlaceholder": "Yaca ni iLawalawa (kena ivakaraitaki: Na Mathletes)",
    "subjectPlaceholder": "Lesoni (kena ivakaraitaki: Algebra)",
    "classPlaceholder": "Rumunikalasi / Vanua (kena ivakaraitaki: Vale ni Vola)",
    "btnCreateGroup": "Bulia na iLawalawa ✨",
    "workshopsTitle": "🏆 Vuli Vakatabakidua ni Rawaka",
    "noWorkshops": "Sega na vuli vakatabakidua e tu mai liu.",
    "adminPost": "🛠️ e Liuliu: Tabaka na Vuli Vakatabakidua",
    "wsTitlePlaceholder": "Yaca ni Vuli Vakatabakidua",
    "wsDescPlaceholder": "iVakamacala",
    "btnPostWorkshop": "Tabaka na Vuli Vakatabakidua 📢"
  },
  "home": {
    "schoolName": "🏫 Koronivuli Torocake e Elmore",
    "heroTitle": "PAPA NI TUKUTUKU NI KALABU",
    "heroDesc": "Volayaca me gonevuli, curuma nomu loka, lewena na kalabu lialia ni koronivuli, ka raica o cei tale e tiko ena timi!",
    "dbPendingTitle": "⚠️ Waraki tiko na Database Setup!",
    "dbPendingDesc": "Yalo vinaka biuta na nomu vosuniwasi dodonu ni MySQL ena",
    "dbPendingDesc2": "ka cicivaka na ivakaro ni teitei:",
    "enrolledStudents": "Gonevuli Volayaca",
    "activeClubs": "Kalabu Bulabula ni Koronivuli",
    "notice": "\"Notisi: Ena Seeding e tiko kina na itukutuku kei Gumball, Darwin, Penny, Carrie, Anais, Bobert, kei Banana Joe. E veivakasalataki o Qasenivuli Levu Brown ni sa tabu sara na mama kuliniji ena sala.\"",
    "newStudentTitle": "Gonevuli Vou?",
    "newStudentDesc": "Bulia e dua na akaude ena nomu ID vakadonui ni Gonevuli e Elmore High.",
    "enrollBtn": "Volayaca Oqo ✨",
    "currentStudentTitle": "Gonevuli ni Gauna Oqo",
    "currentStudentDesc": "Curuma na nomu dashboard me lewa na kalabu se kerea na veitokoni.",
    "hallwayBtn": "Lako ki na Sala 🏃",
    "loginBtn": "Curu Mai 🔐"
  },
  "club": {
    "proposedBy": "Vakatututaki mai vei",
    "leave": "Biu 🚪",
    "join": "Curuma 🎒",
    "viewRoster": "Raica na Lewenikalabu →",
    "activeMembers": "lewenikalabu bulabula",
    "activeMember": "lewenikalabu bulabula"
  }
}
